distanse_finner/__init__.py
distanse_finner/distanse_finner.py
distanse_finner-0.0.10.dist-info/METADATA
distanse_finner-0.0.10.dist-info/WHEEL
distanse_finner-0.0.10.dist-info/top_level.txt
distanse_finner-0.0.10.dist-info/RECORD
