Metadata-Version: 2.1
Name: distanse-finner
Version: 0.0.10
Summary: Verktøy for å finne avstander fra posisjonsdata.
Author: Marie Roald
License: MIT
Provides-Extra: gpx
Requires-Dist: gpxpy ; extra == 'gpx'
